clipthread/__init__.py
clipthread/core/__init__.py
clipthread/core/crypto.py
clipthread/core/main.py
clipthread/core/utils.py
clipthread/core/db/__init__.py
clipthread/core/db/clipboard.py
clipthread/core/db/config.py
clipthread/core/db/journal.py
clipthread/core/db/utils.py
clipthread/core/models/__init__.py
clipthread/core/models/clipboard.py
clipthread/core/models/journal.py
clipthread_core-0.0.3.dist-info/METADATA
clipthread_core-0.0.3.dist-info/WHEEL
clipthread_core-0.0.3.dist-info/licenses/LICENSE
clipthread_core-0.0.3.dist-info/RECORD
